pypeduct/__init__.py
pypeduct/exceptions.py
pypeduct/helpers.py
pypeduct/pyping.py
pypeduct/transformer.py
pypeduct-0.9.1.dist-info/licenses/LICENSE
pypeduct-0.9.1.dist-info/METADATA
pypeduct-0.9.1.dist-info/WHEEL
pypeduct-0.9.1.dist-info/top_level.txt
pypeduct-0.9.1.dist-info/RECORD
