Metadata-Version: 2.4
Name: pypeduct
Version: 0.9.1
Summary: Pypes >> Python 3.
Author-email: Anselm Kiefner <pypeduct-github@anselm.kiefner.de>
License-Expression: MIT
Project-URL: Homepage, https://github.com/amogorkon/pypeduct
Requires-Python: >=3.12
License-File: LICENSE
Dynamic: license-file
